{"postId":5602988,"headline":"8\" Mirror Grinding: Seeing Flaws","publishedAt":"2024-04-17T16:50:10.503Z","state":1,"cws":[],"tags":["hillescopebuilding"],"blocks":[{"type":"attachment","attachment":{"kind":"image","fileURL":"https://staging.cohostcdn.org/attachment/77e103ae-b8e1-4702-a729-e68d86c228c4/IMG_20240417_000708615_1.jpg","previewURL":"https://staging.cohostcdn.org/attachment/77e103ae-b8e1-4702-a729-e68d86c228c4/IMG_20240417_000708615_1.jpg","attachmentId":"77e103ae-b8e1-4702-a729-e68d86c228c4","altText":"","width":1379,"height":1379}},{"type":"attachment","attachment":{"kind":"image","fileURL":"https://staging.cohostcdn.org/attachment/04561744-632f-4cf7-9f50-b01568ea55cc/20240416_233201_124816.jpg","previewURL":"https://staging.cohostcdn.org/attachment/04561744-632f-4cf7-9f50-b01568ea55cc/20240416_233201_124816.jpg","attachmentId":"04561744-632f-4cf7-9f50-b01568ea55cc","altText":"","width":3000,"height":4000}},{"type":"markdown","markdown":{"content":"It's been a while but I gave the 8\" mirror some grinding. I'm on my way back to sphere, undoing parabolizing attempt #2. 30 minutes of grinding seems to have created some turned down edge and a hole in the middle. Great."}},{"type":"markdown","markdown":{"content":"I put the mirror into the telescope, leaned it against a big crate again, and I was able to use it to see the moon! It's amazing that even though I'm not done figuring, it's smooth enough I can see things in space. It was noticeably dimmer and slightly less sharp than in my hadley, which makes sense because the 8\" mirror isn't aluminized."}},{"type":"markdown","markdown":{"content":"Now to keep at it, and then start parabolizing try #3."}}],"pinned":false,"commentsLocked":false,"sharesLocked":false,"singlePostPageUrl":"https://cohost.org/hillexed/post/5602988-8-mirror-grinding"}